{
  "11f5f77d-592f-4355-b2b6-0879123fbab5": {
    "type": "text",
    "name": "Battery Subsystem Analysis \u2014 PA Layer",
    "package_name": "trail-power",
    "path": "packages/trail-power/artifacts/2026-06/11f5f77d-592f-4355-b2b6-0879123fbab5",
    "created_at": "2026-06-10T12:17:50.640582+00:00",
    "updated_at": "2026-06-10T12:17:50.640611+00:00",
    "tags": [
      "battery",
      "PA",
      "NCR18650B",
      "analysis",
      "physical-architecture",
      "store-energy"
    ]
  },
  "03591bcc-7db6-42ad-ae67-dd4117b021a8": {
    "type": "text",
    "name": "RFP TP-BAT-2026-001 \u2014 NCR18650B Procurement",
    "package_name": "trail-power",
    "path": "packages/trail-power/artifacts/2026-06/03591bcc-7db6-42ad-ae67-dd4117b021a8",
    "created_at": "2026-06-10T12:18:04.704016+00:00",
    "updated_at": "2026-06-10T12:18:04.704053+00:00",
    "tags": [
      "RFP",
      "procurement",
      "NCR18650B",
      "battery",
      "TP-BAT-2026-001"
    ]
  },
  "2dca9674-8fff-46fe-9caa-d76141f65b2f": {
    "type": "log_book",
    "name": "Trail Power Engineering Work Log",
    "package_name": "trail-power",
    "path": "packages/trail-power/artifacts/2026-06/2dca9674-8fff-46fe-9caa-d76141f65b2f",
    "created_at": "2026-06-10T12:27:30.767331+00:00",
    "updated_at": "2026-06-10T12:27:30.767359+00:00",
    "tags": [
      "log",
      "work-log",
      "trail-power"
    ]
  },
  "f8869c15-c7cc-47d9-8295-618d0274b50c": {
    "type": "text",
    "name": "Observation \u2014 Panasonic NCR18650B Meets Specified Performance",
    "package_name": "trail-power",
    "path": "packages/trail-power/artifacts/2026-06/f8869c15-c7cc-47d9-8295-618d0274b50c",
    "created_at": "2026-06-10T12:21:53.022072+00:00",
    "updated_at": "2026-06-10T12:21:53.022107+00:00",
    "tags": [
      "observation",
      "NCR18650B",
      "battery",
      "performance",
      "store-energy",
      "verification"
    ]
  },
  "49f24a67-4910-4e2e-bc09-a2cf3d9eab20": {
    "type": "text",
    "name": "Decision \u2014 Continue Evaluation with Panasonic NCR18650B",
    "package_name": "trail-power",
    "path": "packages/trail-power/artifacts/2026-06/49f24a67-4910-4e2e-bc09-a2cf3d9eab20",
    "created_at": "2026-06-10T12:23:12.976173+00:00",
    "updated_at": "2026-06-10T12:23:12.976199+00:00",
    "tags": [
      "decision",
      "NCR18650B",
      "battery",
      "component-selection",
      "evaluation",
      "store-energy"
    ]
  },
  "25a05fcf-50da-4bd3-a07a-9d27daa162cd": {
    "type": "text",
    "name": "Observation \u2014 MBSE-Driven Engineering Approach Shows Strong Value",
    "package_name": "trail-power",
    "path": "packages/trail-power/artifacts/2026-06/25a05fcf-50da-4bd3-a07a-9d27daa162cd",
    "created_at": "2026-06-10T12:27:20.811364+00:00",
    "updated_at": "2026-06-10T12:27:20.811389+00:00",
    "tags": [
      "observation",
      "MBSE",
      "process",
      "traceability",
      "program-reflection",
      "knowledge-management"
    ]
  },
  "f6965579-99e0-48d9-91ef-306a00c66ae8": {
    "type": "text",
    "name": "Issue \u2014 Binary File Upload to Artifact Repo Not Yet Supported",
    "package_name": "trail-power",
    "path": "packages/trail-power/artifacts/2026-06/f6965579-99e0-48d9-91ef-306a00c66ae8",
    "created_at": "2026-06-10T12:39:16.483818+00:00",
    "updated_at": "2026-06-10T12:39:16.483853+00:00",
    "tags": [
      "issue",
      "capability-gap",
      "file-upload",
      "artifact-repo",
      "todo"
    ]
  }
}